leb/just_focus/__init__.py
leb/just_focus/dtypes.py
leb/just_focus/focal_fields.py
leb/just_focus/inputs.py
leb/just_focus/pupil.py
leb/just_focus/plots/__init__.py
leb/just_focus/plots/inputs.py
leb/just_focus/scripts/__init__.py
leb/just_focus/scripts/gaussian.py
leb/just_focus/scripts/halfmoon.py
just_focus-0.3.2.dist-info/METADATA
just_focus-0.3.2.dist-info/WHEEL
just_focus-0.3.2.dist-info/entry_points.txt
just_focus-0.3.2.dist-info/licenses/LICENSE
just_focus-0.3.2.dist-info/RECORD
