Metadata-Version: 2.4
Name: just-focus
Version: 0.3.2
Summary: Vector electromagnetic field calculations in the focus of high NA microscope objectives.
Project-URL: Repository, https://github.com/LEB-EPFL/just-focus
Author-email: Kyle Douglass <kyle.douglass@epfl.ch>
License-Expression: GPL-3.0-or-later
License-File: LICENSE
Keywords: diffraction,electromagnetism,microscopy,richards-wolf
Classifier: Development Status :: 4 - Beta
Classifier: Intended Audience :: Science/Research
Classifier: Programming Language :: Python :: 3
Classifier: Programming Language :: Python :: 3.11
Classifier: Programming Language :: Python :: 3.12
Classifier: Programming Language :: Python :: 3.13
Classifier: Topic :: Scientific/Engineering :: Physics
Requires-Python: >=3.11
Requires-Dist: numpy>=2.3.2
Provides-Extra: plot
Requires-Dist: matplotlib>=3.10.5; extra == 'plot'
Requires-Dist: pyside6>=6.9.1; extra == 'plot'
